[
  {
    "id": "779d1c65-721d-4f13-b9aa-90501697fc40",
    "nickname": "墨染设计师",
    "bio": "热爱把生活画进画布的独立插画师",
    "skills": [
      "UI设计",
      "插画",
      "品牌设计",
      "摄影",
      "手写字"
    ],
    "email": "moran@design.com",
    "createdAt": 1781947726065
  },
  {
    "id": "a1b2c3d4-1111-2222-3333-444455556666",
    "nickname": "星辰程序员",
    "bio": "用代码构建星辰大海的全栈工程师",
    "skills": [
      "TypeScript",
      "React",
      "Node.js",
      "Docker",
      "算法"
    ],
    "email": "starcoder@dev.io",
    "createdAt": 1781947000000
  },
  {
    "id": "b2c3d4e5-2222-3333-4444-555566667777",
    "nickname": "薄荷摄影师",
    "bio": "捕捉世间温柔瞬间的风光摄影师",
    "skills": [
      "风光摄影",
      "人像摄影",
      "后期调色",
      "胶片"
    ],
    "email": "mint@photo.cn",
    "createdAt": 1781946000000
  },
  {
    "id": "c3d4e5f6-3333-4444-5555-666677778888",
    "nickname": "青瓷游戏策划",
    "bio": "热爱创造虚拟世界的游戏设计师",
    "skills": [
      "关卡设计",
      "叙事",
      "Unity",
      "数值平衡"
    ],
    "email": "celadon@game.dev",
    "createdAt": 1781945000000
  },
  {
    "id": "d4e5f6a7-4444-5555-6666-777788889999",
    "nickname": "咖啡字体师",
    "bio": "一杯咖啡一套字，字体排印爱好者",
    "skills": [
      "字体设计",
      "排印",
      "Branding",
      "书籍装帧"
    ],
    "email": "coffee@type.design",
    "createdAt": 1781944000000
  },
  {
    "id": "e5f6a7b8-5555-6666-7777-888899990000",
    "nickname": "极光动效师",
    "bio": "让界面会呼吸的动效设计师",
    "skills": [
      "After Effects",
      "Lottie",
      "3D建模",
      "动效设计"
    ],
    "email": "aurora@motion.art",
    "createdAt": 1781943000000
  },
  {
    "id": "f6a7b8c9-6666-7777-8888-999900001111",
    "nickname": "南风文案",
    "bio": "写东西的，贩卖浪漫和远方",
    "skills": [
      "广告文案",
      "品牌故事",
      "诗歌",
      "剧本"
    ],
    "email": "nanfeng@write.cn",
    "createdAt": 1781942000000
  },
  {
    "id": "a7b8c9d0-7777-8888-9999-000011112222",
    "nickname": "云隐产品经理",
    "bio": "连接用户和技术的思考者",
    "skills": [
      "用户研究",
      "需求分析",
      "原型设计",
      "数据分析"
    ],
    "email": "yunyin@pm.io",
    "createdAt": 1781941000000
  }
]
